{"info":[{"origin": 1927.162, "child": "RA028"}],"duration":[{"start": 18.71, "end": 237.029}],"rabc":[{"start": 18.71, "end": 166.107, "val": "RABC"}],"stages":[{"start": 19.21, "end": 26.782, "val": "greeting"},{"start": 26.852, "end": 75.833, "val": "ball"},{"start": 78.054, "end": 120.894, "val": "book"},{"start": 120.925, "end": 129.587, "val": "hat"},{"start": 141.25, "end": 165.95, "val": "tickle"},{"start": 199.649, "end": 209.729, "val": "name_s"},{"start": 231.684, "end": 237.029, "val": "name_f"}],"red":[{"start": 24.325, "end": 25.117, "val": "child_verbalization"},{"start": 71.815, "end": 73.194, "val": "child_vocalization"},{"start": 75.989, "end": 76.25, "val": "child_vocalization"},{"start": 130.173, "end": 130.639, "val": "child_verbalization"},{"start": 160.639, "end": 161.79, "val": "child_vocalization"}],"green":[{"start": 152.107, "end": 154.655, "val": "gesture_reach"},{"start": 160.7, "end": 163.45, "val": "gesture_reach"}],"blue":[{"start": 21.07, "end": 24.32, "val": "gaze_ex_face"},{"start": 25.279, "end": 25.59, "val": "gaze_ex_face"},{"start": 29.259, "end": 29.48, "val": "gaze_ex_face"},{"start": 35.129, "end": 35.87, "val": "gaze_ex_face"},{"start": 41.737, "end": 42.41, "val": "gaze_ex_face"},{"start": 47.74, "end": 48.42, "val": "gaze_ex_face"},{"start": 50.632, "end": 51.77, "val": "gaze_ex_face"},{"start": 52.927, "end": 53.799, "val": "gaze_ex_face"},{"start": 58.06, "end": 58.64, "val": "gaze_ex_face"},{"start": 64.38, "end": 64.93, "val": "gaze_ex_face"},{"start": 69.12, "end": 71.34, "val": "gaze_ex_face"},{"start": 72.21, "end": 72.765, "val": "gaze_ex_face"},{"start": 76.443, "end": 76.74, "val": "gaze_ex_face"},{"start": 83.14, "end": 83.63, "val": "gaze_ex_face"},{"start": 92.459, "end": 92.591, "val": "gaze_ex_face"},{"start": 99.39, "end": 99.93, "val": "gaze_ex_face"},{"start": 121.365, "end": 124.755, "val": "gaze_ex_face"},{"start": 127.59, "end": 128.135, "val": "gaze_ex_face"},{"start": 147.49, "end": 151.16, "val": "gaze_ex_face"},{"start": 153.785, "end": 154.405, "val": "gaze_ex_face"},{"start": 155.06, "end": 156.55, "val": "gaze_ex_face"},{"start": 157.85, "end": 158.81, "val": "gaze_ex_face"},{"start": 159.33, "end": 160.71, "val": "gaze_ex_face"},{"start": 162.07, "end": 163.38, "val": "gaze_ex_face"},{"start": 164.31, "end": 166.44, "val": "gaze_ex_face"},{"start": 233.939, "end": 234.676, "val": "gaze_ex_face"}],"dashes":[{"start": 27.827, "end": 29.195, "val": "gaze_ball"},{"start": 29.777, "end": 30.245, "val": "gaze_ball"},{"start": 31.2, "end": 34.97, "val": "gaze_ball"},{"start": 35.935, "end": 37.73, "val": "gaze_ball"},{"start": 38.309, "end": 39.415, "val": "gaze_ball"},{"start": 40.507, "end": 41.655, "val": "gaze_ball"},{"start": 49.81, "end": 50.6, "val": "gaze_ball"},{"start": 51.834, "end": 52.8, "val": "gaze_ball"},{"start": 53.829, "end": 56.034, "val": "gaze_ball"},{"start": 57.107, "end": 58.007, "val": "gaze_ball"},{"start": 58.665, "end": 60.145, "val": "gaze_ball"},{"start": 63.515, "end": 64.335, "val": "gaze_ball"},{"start": 65.75, "end": 67.122, "val": "gaze_ball"},{"start": 67.58, "end": 67.97, "val": "gaze_ball"},{"start": 68.58, "end": 69.035, "val": "gaze_ball"},{"start": 71.42, "end": 72.16, "val": "gaze_ball"},{"start": 72.797, "end": 74.17, "val": "gaze_ball"},{"start": 79.94, "end": 83.0, "val": "gaze_book"},{"start": 83.68, "end": 92.36, "val": "gaze_book"},{"start": 92.657, "end": 99.109, "val": "gaze_book"},{"start": 99.975, "end": 121.015, "val": "gaze_book"},{"start": 142.252, "end": 142.805, "val": "gaze_ex_hands"},{"start": 144.974, "end": 145.737, "val": "gaze_ex_hands"},{"start": 151.22, "end": 153.73, "val": "gaze_ex_hands"},{"start": 156.66, "end": 157.8, "val": "gaze_ex_hands"},{"start": 158.84, "end": 159.25, "val": "gaze_ex_hands"},{"start": 117.05, "end": 117.35, "val": "child_whine_cry"},{"start": 146.65, "end": 146.859, "val": "child_whine_cry"},{"start": 163.084, "end": 163.424, "val": "child_laugh"}],"linebreak":[{"start": 76.414, "end": 78.63, "val": "c_disengage"},{"start": 78.66, "end": 82.714, "val": "c_away"},{"start": 125.545, "end": 128.05, "val": "c_disengage"},{"start": 128.067, "end": 143.017, "val": "c_away"}],"filled":[{"start": 27.595, "end": 29.365, "val": "look at my ball"},{"start": 50.099, "end": 51.497, "val": "look at my ball"},{"start": 78.995, "end": 80.25, "val": "look at my book"},{"start": 90.75, "end": 92.117, "val": "what's next?"},{"start": 95.755, "end": 96.917, "val": "where is the ... ?"},{"start": 100.229, "end": 101.55, "val": "where is the ... ?"},{"start": 125.099, "end": 126.362, "val": "where is the book?"},{"start": 126.517, "end": 128.517, "val": "it's a hat! It's on my head!"}],"unfilled":[{"start": 21.85, "end": 24.284, "val": "play with new toys"},{"start": 31.884, "end": 32.975, "val": "let's play ball"},{"start": 33.564, "end": 37.917, "val": "one, two, three, ..."},{"start": 38.855, "end": 40.384, "val": "go!"},{"start": 40.95, "end": 42.585, "val": "ready, set, ..."},{"start": 52.494, "end": 54.349, "val": "ready, set, ..."},{"start": 55.089, "end": 56.25, "val": "go!"},{"start": 57.215, "end": 58.76, "val": "ready, set, ..."},{"start": 59.397, "end": 61.097, "val": "go!"},{"start": 63.822, "end": 65.717, "val": "ready, set, ..."},{"start": 66.16, "end": 68.197, "val": "go!"},{"start": 68.98, "end": 70.784, "val": "ready, set, ..."},{"start": 73.084, "end": 75.75, "val": "go!"},{"start": 141.549, "end": 146.762, "val": "gonna get you"},{"start": 146.984, "end": 148.784, "val": "tickle tickle tickle"},{"start": 149.584, "end": 153.05, "val": "gonna get you"},{"start": 153.32, "end": 154.584, "val": "tickle tickle tickle"},{"start": 155.584, "end": 159.35, "val": "gonna get you"},{"start": 162.08, "end": 164.357, "val": "tickle tickle tickle"}],"redfilled":[{"start": 19.715, "end": 20.889, "val": "c_name"},{"start": 199.65, "end": 200.654, "val": "c_name"},{"start": 203.045, "end": 204.084, "val": "c_name"},{"start": 207.18, "end": 208.35, "val": "c_name"},{"start": 231.684, "end": 232.697, "val": "c_name"}],"examiner":[],"socialbid":[]}